fanfic_scraper/__init__.py
fanfic_scraper/base_fanfic.py
fanfic_scraper/cui.py
fanfic_scraper/current_fanfic.py
fanfic_scraper/db_pony.py
fanfic_scraper/extractors/__init__.py
fanfic_scraper/extractors/fanfictionnet.py
fanfic_scraper/extractors/hpfanficarchive.py
fanfic_scraper/fanfic_scraper.py
fanfic_scraper/ff.py
fanfic_scraper/ff_fif.py
fanfic_scraper/ff_h2t.py
fanfic_scraper/ff_rf.py
fanfic_scraper/ffdl.py
fanfic_scraper-0.7.4.dist-info/entry_points.txt
fanfic_scraper-0.7.4.dist-info/LICENSE
fanfic_scraper-0.7.4.dist-info/WHEEL
fanfic_scraper-0.7.4.dist-info/METADATA
fanfic_scraper-0.7.4.dist-info/RECORD
