Metadata-Version: 2.1
Name: fanfic-scraper
Version: 0.7.4
Summary: Scrapes fanfics, maintains download db, organizes folders when reading.
License: MIT
Author: Kevin Meredith
Author-email: kevin@meredithkm.info
Requires-Python: >=3.5,<4.0
Classifier: License :: OSI Approved :: MIT License
Classifier: Programming Language :: Python :: 3
Classifier: Programming Language :: Python :: 3.5
Classifier: Programming Language :: Python :: 3.6
Classifier: Programming Language :: Python :: 3.7
Requires-Dist: beautifulsoup4 (>=4.7,<5.0)
Requires-Dist: fake_useragent (>=0.1.11,<0.2.0)
Requires-Dist: html2text (>=2018.1,<2019.0)
Requires-Dist: html5lib (>=1.0,<2.0)
Requires-Dist: pony (>=0.7.10,<0.8.0)
Requires-Dist: pysocks (>=1.7,<2.0)
Requires-Dist: requests (>=2.22,<3.0)
Requires-Dist: tldextract (>=2.2,<3.0)
